uncertainties/__init__.py
uncertainties/core.py
uncertainties/umath.py
uncertainties/umath_core.py
uncertainties/version.py
uncertainties/unumpy/__init__.py
uncertainties/unumpy/core.py
uncertainties/unumpy/ulinalg.py
uncertainties-3.2.2.dist-info/LICENSE.txt
uncertainties-3.2.2.dist-info/METADATA
uncertainties-3.2.2.dist-info/WHEEL
uncertainties-3.2.2.dist-info/top_level.txt
uncertainties-3.2.2.dist-info/RECORD
