Metadata-Version: 2.1
Name: uncertainties
Version: 3.2.2
Summary: calculations with values with uncertainties, error propagation
Author-email: "Eric O. LEBIGOT (EOL)" <eric.lebigot@normalesup.org>
License: Revised BSD License
Project-URL: Documentation, https://uncertainties.readthedocs.io/
Project-URL: Repository, https://github.com/lmfit/uncertainties
Project-URL: Issues, https://github.com/lmfit/uncertainties/issues
Project-URL: Changelog, https://github.com/lmfit/uncertainties/blob/master/CHANGES.rst
Keywords: error propagation,uncertainties,uncertainty calculations,standard deviation,derivatives,partial derivatives,differentiation
Classifier: Development Status :: 5 - Production/Stable
Classifier: Intended Audience :: Developers
Classifier: Intended Audience :: Education
Classifier: Intended Audience :: Other Audience
Classifier: Intended Audience :: Science/Research
Classifier: License :: OSI Approved :: BSD License
Classifier: Operating System :: OS Independent
Classifier: Programming Language :: Python
Classifier: Programming Language :: Python :: 3
Classifier: Programming Language :: Python :: 3.8
Classifier: Programming Language :: Python :: 3.9
Classifier: Programming Language :: Python :: 3.10
Classifier: Programming Language :: Python :: 3.11
Classifier: Programming Language :: Python :: 3.12
Classifier: Programming Language :: Python :: Implementation :: Jython
Classifier: Programming Language :: Python :: Implementation :: PyPy
Classifier: Topic :: Education
Classifier: Topic :: Scientific/Engineering
Classifier: Topic :: Scientific/Engineering :: Mathematics
Classifier: Topic :: Scientific/Engineering :: Physics
Classifier: Topic :: Software Development
Classifier: Topic :: Software Development :: Libraries
Classifier: Topic :: Software Development :: Libraries :: Python Modules
Classifier: Topic :: Utilities
Requires-Python: >=3.8
License-File: LICENSE.txt
Provides-Extra: arrays
Requires-Dist: numpy; extra == "arrays"
Provides-Extra: test
Requires-Dist: pytest; extra == "test"
Requires-Dist: pytest_cov; extra == "test"
Provides-Extra: doc
Requires-Dist: sphinx; extra == "doc"
Requires-Dist: sphinx-copybutton; extra == "doc"
Requires-Dist: python-docs-theme; extra == "doc"
Provides-Extra: all
Requires-Dist: uncertainties[arrays,doc,test]; extra == "all"
